pythril/__init__.py
pythril/counters.py
pythril-0.0.1.dist-info/LICENSE
pythril-0.0.1.dist-info/METADATA
pythril-0.0.1.dist-info/WHEEL
pythril-0.0.1.dist-info/entry_points.txt
pythril-0.0.1.dist-info/top_level.txt
pythril-0.0.1.dist-info/RECORD
