Metadata-Version: 2.1
Name: pythril
Version: 0.0.1
Summary: Python data science tools for large data sets.
Home-page: https://github.com/pubds/pythril
Author: Shawn M. O'Hare
Author-email: shawn@shawnohare.com
Maintainer: Shawn M. O'Hare
Maintainer-email: shawn@shawnohare.com
License: MIT License
Keywords: data science
Platform: UNKNOWN
Classifier: Programming Language :: Python :: 3
Classifier: Programming Language :: Python :: 3.8
Requires-Python: >=3.8
Requires-Dist: pip (>=19)
Requires-Dist: setuptools (>=41)
Provides-Extra: dev
Requires-Dist: pytest ; extra == 'dev'
Provides-Extra: dist
Requires-Dist: twine ; extra == 'dist'
